apiverve_airquality/__init__.py
apiverve_airquality/apiClient.py
apiverve_airquality/exceptions.py
apiverve_airquality/setup.py
apiverve_airquality/setup_dep.py
apiverve_airquality/tests/__init__.py
apiverve_airquality/tests/test_api.py
apiverve_airquality-1.1.8.dist-info/LICENSE
apiverve_airquality-1.1.8.dist-info/METADATA
apiverve_airquality-1.1.8.dist-info/WHEEL
apiverve_airquality-1.1.8.dist-info/top_level.txt
apiverve_airquality-1.1.8.dist-info/RECORD
